<?xml version="1.0" encoding="utf-8"?>
<clothing-items>
 <clothing>
  <id>
   706725451
  </id>
  <name>
   Brooks Sweater X-9033
  </name>
  <category>
   Sweater
  </category>
  <size>
   M
  </size>
  <color>
   Желтый
  </color>
  <material>
   Шерсть
  </material>
  <price>
   246951
  </price>
  <rating>
   2.47
  </rating>
  <reviews>
   150975
  </reviews>
  <new>
   -
  </new>
  <sporty>
   no
  </sporty>
 </clothing>
 <clothing>
  <id>
   935352863
  </id>
  <name>
   Addidas Belts F-7068
  </name>
  <category>
   Belts
  </category>
  <size>
   XXL
  </size>
  <color>
   Голубой
  </color>
  <material>
   Полиэстер
  </material>
  <price>
   508159
  </price>
  <rating>
   2.68
  </rating>
  <reviews>
   828508
  </reviews>
  <new>
   -
  </new>
  <exclusive>
   yes
  </exclusive>
  <sporty>
   yes
  </sporty>
 </clothing>
 <clothing>
  <id>
   952098259
  </id>
  <name>
   Adidas Jeans Y-2668
  </name>
  <category>
   Jeans
  </category>
  <size>
   XL
  </size>
  <color>
   Голубой
  </color>
  <material>
   Шелк
  </material>
  <price>
   405965
  </price>
  <rating>
   1.89
  </rating>
  <reviews>
   892671
  </reviews>
  <exclusive>
   no
  </exclusive>
  <sporty>
   no
  </sporty>
 </clothing>
 <clothing>
  <id>
   656476884
  </id>
  <name>
   Nike Dress F-8938
  </name>
  <category>
   Dress
  </category>
  <size>
   L
  </size>
  <color>
   Желтый
  </color>
  <material>
   Шерсть
  </material>
  <price>
   525276
  </price>
  <rating>
   3.88
  </rating>
  <reviews>
   539417
  </reviews>
  <sporty>
   yes
  </sporty>
 </clothing>
 <clothing>
  <id>
   958419865
  </id>
  <name>
   Under Armour T-shirt F-1706
  </name>
  <category>
   T-shirt
  </category>
  <size>
   XL
  </size>
  <color>
   Желтый
  </color>
  <material>
   Хлопок
  </material>
  <price>
   206454
  </price>
  <rating>
   2.37
  </rating>
  <reviews>
   872690
  </reviews>
  <new>
   +
  </new>
  <sporty>
   yes
  </sporty>
 </clothing>
 <clothing>
  <id>
   607121087
  </id>
  <name>
   Lacoste Jacket Z-3148
  </name>
  <category>
   Jacket
  </category>
  <size>
   L
  </size>
  <color>
   Фиолетовый
  </color>
  <material>
   Шелк
  </material>
  <price>
   114517
  </price>
  <rating>
   2.17
  </rating>
  <reviews>
   822070
  </reviews>
  <new>
   -
  </new>
  <exclusive>
   yes
  </exclusive>
  <sporty>
   no
  </sporty>
 </clothing>
 <clothing>
  <id>
   234569433
  </id>
  <name>
   Brooks Skirt P-7420
  </name>
  <category>
   Skirt
  </category>
  <size>
   S
  </size>
  <color>
   Фиолетовый
  </color>
  <material>
   Полиэстер
  </material>
  <price>
   444579
  </price>
  <rating>
   3.25
  </rating>
  <reviews>
   608743
  </reviews>
  <new>
   +
  </new>
  <sporty>
   no
  </sporty>
 </clothing>
 <clothing>
  <id>
   362933968
  </id>
  <name>
   Asics Belts R-6156
  </name>
  <category>
   Belts
  </category>
  <size>
   XXL
  </size>
  <color>
   Голубой
  </color>
  <material>
   Шелк
  </material>
  <price>
   651902
  </price>
  <rating>
   3.68
  </rating>
  <reviews>
   281593
  </reviews>
  <new>
   -
  </new>
  <sporty>
   yes
  </sporty>
 </clothing>
 <clothing>
  <id>
   267208524
  </id>
  <name>
   Addidas Socks P-3763
  </name>
  <category>
   Socks
  </category>
  <size>
   XXL
  </size>
  <color>
   Фиолетовый
  </color>
  <material>
   Шелк
  </material>
  <price>
   904153
  </price>
  <rating>
   2.44
  </rating>
  <reviews>
   861592
  </reviews>
  <new>
   -
  </new>
  <sporty>
   no
  </sporty>
 </clothing>
 <clothing>
  <id>
   993742428
  </id>
  <name>
   Addidas Sweater B-4545
  </name>
  <category>
   Sweater
  </category>
  <size>
   S
  </size>
  <color>
   Желтый
  </color>
  <material>
   Полиэстер
  </material>
  <price>
   505305
  </price>
  <rating>
   3.05
  </rating>
  <reviews>
   974282
  </reviews>
  <new>
   +
  </new>
  <sporty>
   no
  </sporty>
 </clothing>
 <clothing>
  <id>
   644176707
  </id>
  <name>
   Reebok Dress Y-3385
  </name>
  <category>
   Dress
  </category>
  <size>
   XXL
  </size>
  <color>
   Красный
  </color>
  <material>
   Полиэстер
  </material>
  <price>
   148944
  </price>
  <rating>
   3.06
  </rating>
  <reviews>
   574907
  </reviews>
 </clothing>
 <clothing>
  <id>
   309322421
  </id>
  <name>
   Reebok Umbrellas K-9314
  </name>
  <category>
   Umbrellas
  </category>
  <size>
   M
  </size>
  <color>
   Зеленый
  </color>
  <material>
   Вискоза
  </material>
  <price>
   317176
  </price>
  <rating>
   1.03
  </rating>
  <reviews>
   350932
  </reviews>
  <new>
   +
  </new>
  <sporty>
   yes
  </sporty>
 </clothing>
 <clothing>
  <id>
   749391094
  </id>
  <name>
   New Balance Dress T-4003
  </name>
  <category>
   Dress
  </category>
  <size>
   XL
  </size>
  <color>
   Зеленый
  </color>
  <material>
   Нейлон
  </material>
  <price>
   911430
  </price>
  <rating>
   2.48
  </rating>
  <reviews>
   140206
  </reviews>
  <exclusive>
   yes
  </exclusive>
  <sporty>
   yes
  </sporty>
 </clothing>
 <clothing>
  <id>
   141605715
  </id>
  <name>
   Vans T-shirt R-5630
  </name>
  <category>
   T-shirt
  </category>
  <size>
   XL
  </size>
  <color>
   Красный
  </color>
  <material>
   Вискоза
  </material>
  <price>
   414728
  </price>
  <rating>
   1.23
  </rating>
  <reviews>
   50045
  </reviews>
  <new>
   +
  </new>
  <exclusive>
   no
  </exclusive>
  <sporty>
   yes
  </sporty>
 </clothing>
 <clothing>
  <id>
   344093744
  </id>
  <name>
   Addidas Belts P-9782
  </name>
  <category>
   Belts
  </category>
  <size>
   XXL
  </size>
  <color>
   Фиолетовый
  </color>
  <material>
   Полиэстер
  </material>
  <price>
   863580
  </price>
  <rating>
   1.32
  </rating>
  <reviews>
   726872
  </reviews>
  <new>
   -
  </new>
  <sporty>
   no
  </sporty>
 </clothing>
 <clothing>
  <id>
   296773202
  </id>
  <name>
   DC Hat O-4378
  </name>
  <category>
   Hat
  </category>
  <size>
   M
  </size>
  <color>
   Красный
  </color>
  <material>
   Лен
  </material>
  <price>
   776545
  </price>
  <rating>
   4.69
  </rating>
  <reviews>
   547275
  </reviews>
  <new>
   -
  </new>
  <exclusive>
   no
  </exclusive>
 </clothing>
 <clothing>
  <id>
   687971311
  </id>
  <name>
   PleinSport Socks F-1397
  </name>
  <category>
   Socks
  </category>
  <size>
   M
  </size>
  <color>
   Оранжевый
  </color>
  <material>
   Полиэстер
  </material>
  <price>
   374876
  </price>
  <rating>
   4.39
  </rating>
  <reviews>
   143211
  </reviews>
  <exclusive>
   yes
  </exclusive>
  <sporty>
   no
  </sporty>
 </clothing>
 <clothing>
  <id>
   966227054
  </id>
  <name>
   Ellesse Hat W-4432
  </name>
  <category>
   Hat
  </category>
  <size>
   L
  </size>
  <color>
   Зеленый
  </color>
  <material>
   Хлопок
  </material>
  <price>
   602282
  </price>
  <rating>
   2.3
  </rating>
  <reviews>
   84061
  </reviews>
  <new>
   -
  </new>
  <sporty>
   yes
  </sporty>
 </clothing>
 <clothing>
  <id>
   537032492
  </id>
  <name>
   Converse Gloves T-2392
  </name>
  <category>
   Gloves
  </category>
  <size>
   XXL
  </size>
  <color>
   Красный
  </color>
  <material>
   Нейлон
  </material>
  <price>
   379017
  </price>
  <rating>
   2.02
  </rating>
  <reviews>
   789673
  </reviews>
  <sporty>
   no
  </sporty>
 </clothing>
 <clothing>
  <id>
   102065528
  </id>
  <name>
   Brooks Blouse J-9541
  </name>
  <category>
   Blouse
  </category>
  <size>
   S
  </size>
  <color>
   Желтый
  </color>
  <material>
   Хлопок
  </material>
  <price>
   740383
  </price>
  <rating>
   4.08
  </rating>
  <reviews>
   270507
  </reviews>
  <exclusive>
   yes
  </exclusive>
  <sporty>
   no
  </sporty>
 </clothing>
 <clothing>
  <id>
   741579426
  </id>
  <name>
   Fila Blouse S-1563
  </name>
  <category>
   Blouse
  </category>
  <size>
   M
  </size>
  <color>
   Синий
  </color>
  <material>
   Полиэстер
  </material>
  <price>
   542095
  </price>
  <rating>
   1.32
  </rating>
  <reviews>
   969075
  </reviews>
 </clothing>
 <clothing>
  <id>
   963632817
  </id>
  <name>
   Fila Skirt N-4139
  </name>
  <category>
   Skirt
  </category>
  <size>
   XXL
  </size>
  <color>
   Оранжевый
  </color>
  <material>
   Хлопок
  </material>
  <price>
   553779
  </price>
  <rating>
   2.31
  </rating>
  <reviews>
   100947
  </reviews>
  <exclusive>
   yes
  </exclusive>
 </clothing>
 <clothing>
  <id>
   413332013
  </id>
  <name>
   New Balance Pants D-7516
  </name>
  <category>
   Pants
  </category>
  <size>
   M
  </size>
  <color>
   Желтый
  </color>
  <material>
   Кожа
  </material>
  <price>
   931992
  </price>
  <rating>
   1.12
  </rating>
  <reviews>
   123775
  </reviews>
  <new>
   +
  </new>
  <sporty>
   yes
  </sporty>
 </clothing>
 <clothing>
  <id>
   870745162
  </id>
  <name>
   PleinSport Sweater G-2414
  </name>
  <category>
   Sweater
  </category>
  <size>
   XL
  </size>
  <color>
   Фиолетовый
  </color>
  <material>
   Полиэстер
  </material>
  <price>
   913298
  </price>
  <rating>
   4.93
  </rating>
  <reviews>
   329148
  </reviews>
  <new>
   +
  </new>
  <exclusive>
   yes
  </exclusive>
 </clothing>
 <clothing>
  <id>
   556024194
  </id>
  <name>
   Vans Shoes E-3137
  </name>
  <category>
   Shoes
  </category>
  <size>
   M
  </size>
  <color>
   Красный
  </color>
  <material>
   Шерсть
  </material>
  <price>
   745205
  </price>
  <rating>
   2.98
  </rating>
  <reviews>
   614486
  </reviews>
  <new>
   -
  </new>
  <exclusive>
   yes
  </exclusive>
 </clothing>
 <clothing>
  <id>
   479617543
  </id>
  <name>
   Brooks Handbags Y-2139
  </name>
  <category>
   Handbags
  </category>
  <size>
   M
  </size>
  <color>
   Фиолетовый
  </color>
  <material>
   Полиэстер
  </material>
  <price>
   410043
  </price>
  <rating>
   3.12
  </rating>
  <reviews>
   53622
  </reviews>
  <exclusive>
   no
  </exclusive>
 </clothing>
 <clothing>
  <id>
   628511075
  </id>
  <name>
   Brooks Hat C-1041
  </name>
  <category>
   Hat
  </category>
  <size>
   M
  </size>
  <color>
   Зеленый
  </color>
  <material>
   Полиэстер
  </material>
  <price>
   635889
  </price>
  <rating>
   4.99
  </rating>
  <reviews>
   647699
  </reviews>
  <new>
   -
  </new>
 </clothing>
 <clothing>
  <id>
   773894085
  </id>
  <name>
   Converse Hat L-3694
  </name>
  <category>
   Hat
  </category>
  <size>
   L
  </size>
  <color>
   Голубой
  </color>
  <material>
   Шелк
  </material>
  <price>
   955501
  </price>
  <rating>
   1.69
  </rating>
  <reviews>
   111039
  </reviews>
  <sporty>
   no
  </sporty>
 </clothing>
 <clothing>
  <id>
   831705652
  </id>
  <name>
   Nike T-shirt D-5571
  </name>
  <category>
   T-shirt
  </category>
  <size>
   XL
  </size>
  <color>
   Синий
  </color>
  <material>
   Шерсть
  </material>
  <price>
   973574
  </price>
  <rating>
   3.65
  </rating>
  <reviews>
   904182
  </reviews>
  <new>
   -
  </new>
  <exclusive>
   no
  </exclusive>
  <sporty>
   yes
  </sporty>
 </clothing>
</clothing-items>
